{
  "project_info": {
    "project_number": "193832834701",
    "project_id": "linkup-app-3d672",
    "storage_bucket": "linkup-app-3d672.firebasestorage.app"
  },
  "client": [
    {
      "client_info": {
        "mobilesdk_app_id": "1:193832834701:android:87cbab084f075dc3e074c4",
        "android_client_info": {
          "package_name": "com.example.linkup_app"
        }
      },
      "oauth_client": [],
      "api_key": [
        {
          "current_key": "AIzaSyC5kGr1VcsOhgYuA_Fys1ZvbSS6pKd89LA"
        }
      ],
      "services": {
        "appinvite_service": {
          "other_platform_oauth_client": []
        }
      }
    }
  ],
  "configuration_version": "1"
}